simauth/__init__.py
simauth-0.0.9.dist-info/METADATA
simauth-0.0.9.dist-info/WHEEL
simauth-0.0.9.dist-info/top_level.txt
simauth-0.0.9.dist-info/RECORD
