Metadata-Version: 2.1
Name: simauth
Version: 0.0.9
Summary: ok
Author: none
Author-email: google@gmail.com
Classifier: Programming Language :: Python :: 3
Classifier: License :: OSI Approved :: MIT License
Classifier: Operating System :: OS Independent
